e7awghal/__init__.py
e7awghal/abstract_cap.py
e7awghal/abstract_register.py
e7awghal/au50rebooter.py
e7awghal/awgctrl.py
e7awghal/awgunit.py
e7awghal/capctrl.py
e7awghal/capdata.py
e7awghal/capparam.py
e7awghal/capunit.py
e7awghal/classification.py
e7awghal/clockcounterctrl.py
e7awghal/clockmaster_hal.py
e7awghal/clockmasterctrl.py
e7awghal/clockmasterrebooter.py
e7awghal/common_defs.py
e7awghal/common_register.py
e7awghal/e7awg_memoryobj.py
e7awghal/e7awg_packet.py
e7awghal/fwtype.py
e7awghal/hbmctrl.py
e7awghal/py.typed
e7awghal/quel1au50_hal.py
e7awghal/simplemulti.py
e7awghal/syncdata.py
e7awghal/versionchecker.py
e7awghal/wavedata.py
e7awghal-0.1.5.dist-info/licenses/LICENSE
e7awghal-0.1.5.dist-info/METADATA
e7awghal-0.1.5.dist-info/WHEEL
e7awghal-0.1.5.dist-info/top_level.txt
e7awghal-0.1.5.dist-info/RECORD
