Metadata-Version: 2.4
Name: e7awghal
Version: 0.1.5
Summary: HAL Library for e7awg
Author-email: quelware Authors <opensource@quel-inc.com>
License-Expression: Apache-2.0
Project-URL: Repository, https://github.com/quel-inc/quelware
Classifier: Programming Language :: Python :: 3
Classifier: Operating System :: OS Independent
Requires-Python: >=3.9
License-File: LICENSE
Requires-Dist: numpy~=1.26.0
Requires-Dist: scipy~=1.13.1
Requires-Dist: pydantic~=2.4
Provides-Extra: dev
Requires-Dist: black; extra == "dev"
Requires-Dist: mypy; extra == "dev"
Requires-Dist: pytest; extra == "dev"
Requires-Dist: pytest-cov; extra == "dev"
Requires-Dist: matplotlib; extra == "dev"
Requires-Dist: quel_ic_config; extra == "dev"
Requires-Dist: ruff>=0.11.13; extra == "dev"
Dynamic: license-file
